uptick_observability/__init__.py
uptick_observability/logging.py
uptick_observability/monkeypatch.py
uptick_observability/celery/__init__.py
uptick_observability/django/__init__.py
uptick_observability/django/middleware.py
uptick_observability/django/settings.py
uptick_observability/dramatiq/__init__.py
uptick_observability/dramatiq/middleware.py
uptick_observability/fastapi/__init__.py
uptick_observability-0.3.0.dist-info/METADATA
uptick_observability-0.3.0.dist-info/WHEEL
uptick_observability-0.3.0.dist-info/RECORD
