Metadata-Version: 2.4
Name: uptick-observability
Version: 0.3.0
Summary: Add your description here
Author-email: William Chu <william.chu@uptickhq.com>
Requires-Python: >=3.11
Requires-Dist: botocore>=1.35.4
Requires-Dist: opentelemetry-distro>=0.54b1
Requires-Dist: opentelemetry-exporter-otlp>=1.25.0
Requires-Dist: opentelemetry-instrumentation-asgi>=0.54b1
Requires-Dist: opentelemetry-instrumentation-botocore>=0.54b1
Requires-Dist: opentelemetry-instrumentation-grpc>=0.54b1
Requires-Dist: opentelemetry-instrumentation-logging>=0.54b1
Requires-Dist: opentelemetry-instrumentation-psycopg2>=0.54b1
Requires-Dist: opentelemetry-instrumentation-requests>=0.54b1
Requires-Dist: opentelemetry-instrumentation-urllib3>=0.54b1
Requires-Dist: opentelemetry-instrumentation-urllib>=0.54b1
Provides-Extra: celery
Requires-Dist: opentelemetry-instrumentation-celery>=0.54b1; extra == 'celery'
Provides-Extra: django
Requires-Dist: opentelemetry-instrumentation-django>=0.54b1; extra == 'django'
Provides-Extra: fastapi
Requires-Dist: opentelemetry-instrumentation-fastapi>=0.54b1; extra == 'fastapi'
